mdkit/__init__.py
mdkit/amber/PROTON_INFO
mdkit/amber/__init__.py
mdkit/amber/ambertools.py
mdkit/amber/atomic_ions.cmd
mdkit/amber/clustering.py
mdkit/amber/minimization.py
mdkit/namd/__init__.py
mdkit/namd/namdtools.py
mdkit/utility/__init__.py
mdkit/utility/babel.py
mdkit/utility/mol2.py
mdkit/utility/pdb.py
mdkit/utility/reader.py
mdkit/utility/utils.py
mdkit/utility/writer.py
mdkit-0.1.3.data/scripts/cluster_w_amber.py
mdkit-0.1.3.data/scripts/minimize_w_amber.py
mdkit-0.1.3.data/scripts/pdb2mol2
mdkit-0.1.3.data/scripts/prepare_md.py
mdkit-0.1.3.data/scripts/restart_md.py
mdkit-0.1.3.data/scripts/run_mmpbsa.py
mdkit-0.1.3.dist-info/METADATA
mdkit-0.1.3.dist-info/WHEEL
mdkit-0.1.3.dist-info/top_level.txt
mdkit-0.1.3.dist-info/RECORD
