Metadata-Version: 2.1
Name: mdkit
Version: 0.1.3
Summary: Tools to prepare and analyze MD simulations conducted with popular MD packages
Home-page: UNKNOWN
Author: UNKNOWN
Author-email: UNKNOWN
License: LICENSE.txt
Platform: UNKNOWN
Requires-Dist: networkx (==2.2)
Requires-Dist: numpy (==1.16.0)
Requires-Dist: cython (==0.29.2)
